flask_oauthres/__init__.py
flask_oauthres/oauth2.py
Flask_OAuthRes-0.3.0.dist-info/AUTHORS
Flask_OAuthRes-0.3.0.dist-info/LICENSE
Flask_OAuthRes-0.3.0.dist-info/METADATA
Flask_OAuthRes-0.3.0.dist-info/WHEEL
Flask_OAuthRes-0.3.0.dist-info/top_level.txt
Flask_OAuthRes-0.3.0.dist-info/RECORD
